dl_d2l
