Metadata-Version: 2.4
Name: dl_d2l
Version: 1.0.27
Summary: dl_d2l
Home-page: https://github.com/Castlebin/d2l_torch
Author: d2l
Author-email: d2l@qq.com
Classifier: Programming Language :: Python :: 3.9
Classifier: License :: OSI Approved :: Apache Software License
Classifier: Operating System :: OS Independent
License-File: LICENSE
Requires-Dist: torch
Dynamic: author
Dynamic: author-email
Dynamic: classifier
Dynamic: description
Dynamic: description-content-type
Dynamic: home-page
Dynamic: license-file
Dynamic: requires-dist
Dynamic: summary
